pythresh/__init__.py
pythresh/version.py
pythresh/models/meta_model_GNB.pkl
pythresh/models/meta_model_GNBC.pkl
pythresh/models/meta_model_GNBM.pkl
pythresh/models/meta_model_LIN.pkl
pythresh/models/rank_model_XGB.json
pythresh/thresholds/__init__.py
pythresh/thresholds/aucp.py
pythresh/thresholds/base.py
pythresh/thresholds/boot.py
pythresh/thresholds/chau.py
pythresh/thresholds/clf.py
pythresh/thresholds/clust.py
pythresh/thresholds/comb.py
pythresh/thresholds/cpd.py
pythresh/thresholds/decomp.py
pythresh/thresholds/dsn.py
pythresh/thresholds/dummy.py
pythresh/thresholds/eb.py
pythresh/thresholds/fgd.py
pythresh/thresholds/filter.py
pythresh/thresholds/fwfm.py
pythresh/thresholds/gamgmm.py
pythresh/thresholds/gesd.py
pythresh/thresholds/hist.py
pythresh/thresholds/iqr.py
pythresh/thresholds/karch.py
pythresh/thresholds/mad.py
pythresh/thresholds/mcst.py
pythresh/thresholds/meta.py
pythresh/thresholds/mixmod.py
pythresh/thresholds/moll.py
pythresh/thresholds/mtt.py
pythresh/thresholds/ocsvm.py
pythresh/thresholds/qmcd.py
pythresh/thresholds/regr.py
pythresh/thresholds/thresh_utility.py
pythresh/thresholds/vae.py
pythresh/thresholds/wind.py
pythresh/thresholds/yj.py
pythresh/thresholds/zscore.py
pythresh/utils/conf.py
pythresh/utils/rank.py
pythresh/utils/rank_utility.py
pythresh-1.0.3.dist-info/licenses/LICENSE
pythresh-1.0.3.dist-info/METADATA
pythresh-1.0.3.dist-info/WHEEL
pythresh-1.0.3.dist-info/top_level.txt
pythresh-1.0.3.dist-info/RECORD
