Metadata-Version: 2.4
Name: pythresh
Version: 1.0.3
Summary: A Python Toolbox for Outlier Detection Thresholding
Home-page: https://github.com/KulikDM/pythresh
Download-URL: https://github.com/KulikDM/pythresh/archive/master.zip
Author: D Kulik
Project-URL: Documentation, https://pythresh.readthedocs.io/en/latest/
Keywords: outlier detection,anomaly detection,thresholding,cutoff,contamintion level,data science,machine learning
Classifier: Development Status :: 5 - Production/Stable
Classifier: Intended Audience :: Education
Classifier: Intended Audience :: Financial and Insurance Industry
Classifier: Intended Audience :: Science/Research
Classifier: Intended Audience :: Developers
Classifier: Intended Audience :: Information Technology
Classifier: License :: OSI Approved :: BSD License
Classifier: Programming Language :: Python :: 3.7
Classifier: Programming Language :: Python :: 3.8
Classifier: Programming Language :: Python :: 3.9
Classifier: Programming Language :: Python :: 3.10
Classifier: Programming Language :: Python :: 3.11
Classifier: Programming Language :: Python :: 3.12
Classifier: Programming Language :: Python :: 3.13
License-File: LICENSE
Requires-Dist: numpy>=1.19
Requires-Dist: pyod
Requires-Dist: scikit-learn>=0.22.0
Requires-Dist: scipy>=1.5.1
Dynamic: author
Dynamic: classifier
Dynamic: description
Dynamic: description-content-type
Dynamic: download-url
Dynamic: home-page
Dynamic: keywords
Dynamic: license-file
Dynamic: project-url
Dynamic: requires-dist
Dynamic: summary
